[
  {
    "host_name": "(ELSC) East London Stripper Collective",
    "title": "(ELSC) East London Stripper Collective (Monday)",
    "event_type": "in_person",
    "price_info": "\u00a316.50",
    "default_duration_mins": 120,
    "recurrence": "Weekly on Mondays at 7-9.00 PM",
    "raw_time": "7-9.00 PM",
    "raw_day": "Monday"
  },
  {
    "host_name": "Adrian Dutton Life Drawing",
    "title": "Adrian Dutton Life Drawing (Monday)",
    "event_type": "hybrid",
    "price_info": "\u00a311 In-person / \u00a38 Online",
    "default_duration_mins": 120,
    "recurrence": "Weekly on Mondays at 7-9.00 PM",
    "raw_time": "7-9.00 PM",
    "raw_day": "Monday"
  },
  {
    "host_name": "North London Life Drawing",
    "title": "North London Life Drawing (Monday)",
    "event_type": "in_person",
    "price_info": "\u00a315",
    "default_duration_mins": 120,
    "recurrence": "Weekly on Mondays at 7-9.00 PM",
    "raw_time": "7-9.00 PM",
    "raw_day": "Monday"
  },
  {
    "host_name": "London Art Drawing ",
    "title": "London Art Drawing  (Tuesday)",
    "event_type": "in_person",
    "price_info": "\u00a3Eventrite",
    "default_duration_mins": 120,
    "recurrence": "Weekly on Tuesdays at 7-9.00 PM",
    "raw_time": "7-9.00 PM",
    "raw_day": "Tuesday"
  },
  {
    "host_name": "2b Or not 2b",
    "title": "2b Or not 2b (Tuesday)",
    "event_type": "in_person",
    "price_info": "\u00a3Eventrite",
    "default_duration_mins": 120,
    "recurrence": "Monthly on Tuesdays at 7-9.00 PM",
    "raw_time": "7-9.00 PM",
    "raw_day": "Tuesday"
  },
  {
    "host_name": "Covent Garden Life Drawing",
    "title": "Covent Garden Life Drawing (Tuesday)",
    "event_type": "in_person",
    "price_info": "\u00a311",
    "default_duration_mins": 120,
    "recurrence": "Weekly on Tuesdays at 7-9.00 PM",
    "raw_time": "7-9.00 PM",
    "raw_day": "Tuesday"
  },
  {
    "host_name": "Adrian Dutton Life Drawing\n",
    "title": "Adrian Dutton Life Drawing\n (Tuesday)",
    "event_type": "hybrid",
    "price_info": "\u00a311 In-person / \u00a38 Online",
    "default_duration_mins": 120,
    "recurrence": "Weekly on Tuesdays at 7-9.00 PM",
    "raw_time": "7-9.00 PM",
    "raw_day": "Tuesday"
  },
  {
    "host_name": "London Drawing",
    "title": "London Drawing (Tuesday)",
    "event_type": "in_person",
    "price_info": "\u00a315 (10)",
    "default_duration_mins": 120,
    "recurrence": "Weekly on Tuesdays at 7-9 PM",
    "raw_time": "7-9 PM",
    "raw_day": "Tuesday"
  },
  {
    "host_name": "London Bridge Life Drawing",
    "title": "London Bridge Life Drawing (Wednesday)",
    "event_type": "in_person",
    "price_info": "\u00a312",
    "default_duration_mins": 120,
    "recurrence": "Weekly on Wednesdays at 7-9.00 PM",
    "raw_time": "7-9.00 PM",
    "raw_day": "Wednesday"
  },
  {
    "host_name": "Covent Garden Life Drawing",
    "title": "Covent Garden Life Drawing (Wednesday)",
    "event_type": "in_person",
    "price_info": "\u00a311",
    "default_duration_mins": 120,
    "recurrence": "Weekly on Wednesdays at 7-9.00 PM",
    "raw_time": "7-9.00 PM",
    "raw_day": "Wednesday"
  },
  {
    "host_name": "Adrian Dutton Life Drawing",
    "title": "Adrian Dutton Life Drawing (Wednesday)",
    "event_type": "hybrid",
    "price_info": "\u00a311 In-person / \u00a38 Online",
    "default_duration_mins": 120,
    "recurrence": "Weekly on Wednesdays at 7-9.00 PM",
    "raw_time": "7-9.00 PM",
    "raw_day": "Wednesday"
  },
  {
    "host_name": "North London Life Drawing",
    "title": "North London Life Drawing (Wednesday)",
    "event_type": "in_person",
    "price_info": "\u00a311",
    "default_duration_mins": 120,
    "recurrence": "Weekly on Wednesdays at 11-1.00 AM",
    "raw_time": "11-1.00 AM",
    "raw_day": "Wednesday"
  },
  {
    "host_name": "London Drawing",
    "title": "London Drawing (Wednesday)",
    "event_type": "in_person",
    "price_info": "\u00a315 (10)",
    "default_duration_mins": 120,
    "recurrence": "Weekly on Wednesdays at 6:30-8:30 PM",
    "raw_time": "6:30-8:30 PM",
    "raw_day": "Wednesday"
  },
  {
    "host_name": "Leytonstone Life Drawing ",
    "title": "Leytonstone Life Drawing  (Wednesday)",
    "event_type": "in_person",
    "price_info": "\u00a314",
    "default_duration_mins": 120,
    "recurrence": "Weekly on Wednesdays at 7.30-9.30 PM",
    "raw_time": "7.30-9.30 PM",
    "raw_day": "Wednesday"
  },
  {
    "host_name": "Camberwell Life Drawing",
    "title": "Camberwell Life Drawing (Wednesday)",
    "event_type": "in_person",
    "price_info": "\u00a314",
    "default_duration_mins": 120,
    "recurrence": "Weekly on Wednesdays at 7-9.00 PM",
    "raw_time": "7-9.00 PM",
    "raw_day": "Wednesday"
  },
  {
    "host_name": "Life Drawing Art",
    "title": "Life Drawing Art (Thursday)",
    "event_type": "in_person",
    "price_info": "\u00a315",
    "default_duration_mins": 120,
    "recurrence": "Weekly on Thursdays at 7-9.00 PM",
    "raw_time": "7-9.00 PM",
    "raw_day": "Thursday"
  },
  {
    "host_name": "Covent Garden Life Drawing",
    "title": "Covent Garden Life Drawing (Thursday)",
    "event_type": "in_person",
    "price_info": "\u00a311",
    "default_duration_mins": 120,
    "recurrence": "Weekly on Thursdays at 7-9.00 PM",
    "raw_time": "7-9.00 PM",
    "raw_day": "Thursday"
  },
  {
    "host_name": "Adrian Dutton Life Drawing",
    "title": "Adrian Dutton Life Drawing (Thursday)",
    "event_type": "hybrid",
    "price_info": "\u00a311 In-person / \u00a38 Online",
    "default_duration_mins": 120,
    "recurrence": "Weekly on Thursdays at 7-9.00 PM",
    "raw_time": "7-9.00 PM",
    "raw_day": "Thursday"
  },
  {
    "host_name": "Soho Life Drawing",
    "title": "Soho Life Drawing (Thursday)",
    "event_type": "in_person",
    "price_info": "\u00a315",
    "default_duration_mins": 120,
    "recurrence": "Weekly on Thursdays at 6.30-8.30 PM",
    "raw_time": "6.30-8.30 PM",
    "raw_day": "Thursday"
  },
  {
    "host_name": "London Drawing",
    "title": "London Drawing (Thursday)",
    "event_type": "in_person",
    "price_info": "\u00a315 (10)",
    "default_duration_mins": 120,
    "recurrence": "Weekly on Thursdays at 7-9 PM",
    "raw_time": "7-9 PM",
    "raw_day": "Thursday"
  },
  {
    "host_name": "Heskith Hubbard Art Society",
    "title": "Heskith Hubbard Art Society (Friday)",
    "event_type": "in_person",
    "price_info": "\u00a3350 (year)",
    "default_duration_mins": 120,
    "recurrence": "Weekly on Fridays at 6-8:15 PM",
    "raw_time": "6-8:15 PM",
    "raw_day": "Friday"
  },
  {
    "host_name": "Adrian Dutton Life Drawing",
    "title": "Adrian Dutton Life Drawing (Friday)",
    "event_type": "hybrid",
    "price_info": "\u00a311 In-person / \u00a38 Online",
    "default_duration_mins": 120,
    "recurrence": "Weekly on Fridays at 7-9 PM",
    "raw_time": "7-9 PM",
    "raw_day": "Friday"
  },
  {
    "host_name": "Art of Isolation",
    "title": "Art of Isolation (Saturday)",
    "event_type": "in_person",
    "price_info": "\u00a315",
    "default_duration_mins": 120,
    "recurrence": "Weekly on Saturdays at 5-7 PM",
    "raw_time": "5-7 PM",
    "raw_day": "Saturday"
  },
  {
    "host_name": "Soho Life Drawing",
    "title": "Soho Life Drawing (Saturday)",
    "event_type": "in_person",
    "price_info": "\u00a315.00",
    "default_duration_mins": 120,
    "recurrence": "Weekly on Saturdays at 6:30-8:40 PM",
    "raw_time": "6:30-8:40 PM",
    "raw_day": "Saturday"
  },
  {
    "host_name": "London Drawing",
    "title": "London Drawing (Saturday)",
    "event_type": "in_person",
    "price_info": "\u00a315 (10)",
    "default_duration_mins": 120,
    "recurrence": "Weekly on Saturdays at 11-1 PM",
    "raw_time": "11-1 PM",
    "raw_day": "Saturday"
  },
  {
    "host_name": "North London Life Drawing",
    "title": "North London Life Drawing (Saturday)",
    "event_type": "in_person",
    "price_info": "\u00a315",
    "default_duration_mins": 120,
    "recurrence": "Weekly on Saturdays at 11-1PM",
    "raw_time": "11-1PM",
    "raw_day": "Saturday"
  },
  {
    "host_name": "Art of Isolation",
    "title": "Art of Isolation (Sunday)",
    "event_type": "in_person",
    "price_info": "\u00a315",
    "default_duration_mins": 180,
    "recurrence": "Weekly on Sundays at 2-5 PM",
    "raw_time": "2-5 PM",
    "raw_day": "Sunday"
  },
  {
    "host_name": "London Drawing",
    "title": "London Drawing (Sunday)",
    "event_type": "in_person",
    "price_info": "\u00a315 (10)",
    "default_duration_mins": 120,
    "recurrence": "Weekly on Sundays at 1-3 PM",
    "raw_time": "1-3 PM",
    "raw_day": "Sunday"
  },
  {
    "host_name": "Stone Life Drawing",
    "title": "Stone Life Drawing (Sunday)",
    "event_type": "in_person",
    "price_info": "\u00a315",
    "default_duration_mins": 120,
    "recurrence": "Monthly on Sundays at 6-8 PM",
    "raw_time": "6-8 PM",
    "raw_day": "Sunday"
  },
  {
    "host_name": "Scottish Borders Life Drawing",
    "title": "Scottish Borders Life Drawing (Sunday)",
    "event_type": "online",
    "price_info": "\u00a3Donation Online",
    "default_duration_mins": 180,
    "recurrence": "Weekly on Sundays at 1-4 PM",
    "raw_time": "1-4 PM",
    "raw_day": "Sunday"
  },
  {
    "host_name": "Bare Life Drawing",
    "title": "Bare Life Drawing (Monday)",
    "event_type": "in_person",
    "price_info": "\u00a315",
    "default_duration_mins": 120,
    "recurrence": "Weekly on Mondays at 7:30 \u2013 9:30 PM",
    "raw_time": "7:30 \u2013 9:30 PM",
    "raw_day": "Monday"
  },
  {
    "host_name": "Croydon Life Drawing Group",
    "title": "Croydon Life Drawing Group (Saturday)",
    "event_type": "in_person",
    "price_info": "\u00a312.00",
    "default_duration_mins": 180,
    "recurrence": "Fortnightly on Saturdays at 9.30 to 12.30",
    "raw_time": "9.30 to 12.30",
    "raw_day": "Saturday"
  },
  {
    "host_name": "Beehive Pub Tottenham",
    "title": "Beehive Pub Tottenham (Thursday)",
    "event_type": "in_person",
    "price_info": "\u00a310",
    "default_duration_mins": 120,
    "recurrence": "Weekly on Thursdays at 7:00 - 9:00 pm",
    "raw_time": "7:00 - 9:00 pm",
    "raw_day": "Thursday"
  },
  {
    "host_name": "Kilburn Life Drawing",
    "title": "Kilburn Life Drawing (Tuesday)",
    "event_type": "in_person",
    "price_info": "\u00a315",
    "default_duration_mins": 120,
    "recurrence": "Weekly on Tuesdays at 6:30-8:30pm",
    "raw_time": "6:30-8:30pm",
    "raw_day": "Tuesday"
  },
  {
    "host_name": "Ciro\u2019s Life Drawing",
    "title": "Ciro\u2019s Life Drawing (Monday)",
    "event_type": "in_person",
    "price_info": "\u00a316 drop-in (14 bought online)",
    "default_duration_mins": 120,
    "recurrence": "Fortnightly on Mondays at 19:30 - 21:30",
    "raw_time": "19:30 - 21:30",
    "raw_day": "Monday"
  },
  {
    "host_name": "Hampstead Life Drawing",
    "title": "Hampstead Life Drawing (Tuesday)",
    "event_type": "in_person",
    "price_info": "\u00a315.00",
    "default_duration_mins": 120,
    "recurrence": "Weekly on Tuesdays at 19:00",
    "raw_time": "19:00",
    "raw_day": "Tuesday"
  },
  {
    "host_name": "Love2Sketch",
    "title": "Love2Sketch (Tuesday)",
    "event_type": "hybrid",
    "price_info": "\u00a315.00 In-person / \u00a315 Online",
    "default_duration_mins": 120,
    "recurrence": "Weekly on Tuesdays at 19:30",
    "raw_time": "19:30",
    "raw_day": "Tuesday"
  },
  {
    "host_name": "Sevenoaks Drawing Group",
    "title": "Sevenoaks Drawing Group (Thursday)",
    "event_type": "hybrid",
    "price_info": "\u00a315 In-person / \u00a315 Online",
    "default_duration_mins": 180,
    "recurrence": "Weekly on Thursdays at 19:00 pm",
    "raw_time": "19:00 pm",
    "raw_day": "Thursday"
  },
  {
    "host_name": "Mandie Wilde",
    "title": "Mandie Wilde (Wednesday)",
    "event_type": "in_person",
    "price_info": "\u00a315",
    "default_duration_mins": 120,
    "recurrence": "Weekly on Wednesdays at 19:00",
    "raw_time": "19:00",
    "raw_day": "Wednesday"
  },
  {
    "host_name": "Freya\u2019s Fast Poses \u2013 Creative Life Drawing",
    "title": "Freya\u2019s Fast Poses \u2013 Creative Life Drawing (Tuesday)",
    "event_type": "hybrid",
    "price_info": "\u00a315 In-person / \u00a38 Online",
    "default_duration_mins": 90,
    "recurrence": "Weekly on Tuesdays at 19:00",
    "raw_time": "19:00",
    "raw_day": "Tuesday"
  },
  {
    "host_name": "Drink & Draw at The Grosvenor W7",
    "title": "Drink & Draw at The Grosvenor W7 (Wednesday)",
    "event_type": "in_person",
    "price_info": "\u00a312",
    "default_duration_mins": 120,
    "recurrence": "Weekly on Wednesdays at 18:00",
    "raw_time": "18:00",
    "raw_day": "Wednesday"
  },
  {
    "host_name": "Life Drawing at Jazzbourne",
    "title": "Life Drawing at Jazzbourne (Thursday)",
    "event_type": "in_person",
    "price_info": "\u00a310",
    "default_duration_mins": 120,
    "recurrence": "Weekly on Thursdays at 19:30 pm",
    "raw_time": "19:30 pm",
    "raw_day": "Thursday"
  },
  {
    "host_name": "Life Drawing with Anna at Artinc",
    "title": "Life Drawing with Anna at Artinc (Sunday)",
    "event_type": "in_person",
    "price_info": "\u00a335",
    "default_duration_mins": 180,
    "recurrence": "Monthly on Sundays at 11:00",
    "raw_time": "11:00",
    "raw_day": "Sunday"
  },
  {
    "host_name": "London Drawing",
    "title": "London Drawing (Tuesday)",
    "event_type": "in_person",
    "price_info": "\u00a315",
    "default_duration_mins": 120,
    "recurrence": "Weekly on Tuesdays at 19:00",
    "raw_time": "19:00",
    "raw_day": "Tuesday"
  },
  {
    "host_name": "London Drawing",
    "title": "London Drawing (Wednesday)",
    "event_type": "in_person",
    "price_info": "\u00a315",
    "default_duration_mins": 120,
    "recurrence": "Weekly on Wednesdays at 14:00",
    "raw_time": "14:00",
    "raw_day": "Wednesday"
  },
  {
    "host_name": "London Drawing",
    "title": "London Drawing (Thursday)",
    "event_type": "in_person",
    "price_info": "\u00a315",
    "default_duration_mins": 120,
    "recurrence": "Weekly on Thursdays at 19:00",
    "raw_time": "19:00",
    "raw_day": "Thursday"
  },
  {
    "host_name": "London Drawing",
    "title": "London Drawing (Saturday)",
    "event_type": "in_person",
    "price_info": "\u00a315",
    "default_duration_mins": 120,
    "recurrence": "Weekly on Saturdays at 16:00",
    "raw_time": "16:00",
    "raw_day": "Saturday"
  },
  {
    "host_name": "London Drawing",
    "title": "London Drawing (Sunday)",
    "event_type": "in_person",
    "price_info": "\u00a315",
    "default_duration_mins": 120,
    "recurrence": "Weekly on Sundays at 13:00",
    "raw_time": "13:00",
    "raw_day": "Sunday"
  },
  {
    "host_name": "Life Drawing at the Estorick",
    "title": "Life Drawing at the Estorick (Monday)",
    "event_type": "in_person",
    "price_info": "\u00a315",
    "default_duration_mins": 120,
    "recurrence": "Monthly on Mondays at 18:30",
    "raw_time": "18:30",
    "raw_day": "Monday"
  },
  {
    "host_name": "Drop-in Portrait Drawing and Painting Sessions",
    "title": "Drop-in Portrait Drawing and Painting Sessions (Monday)",
    "event_type": "in_person",
    "price_info": "\u00a315",
    "default_duration_mins": 135,
    "recurrence": "Weekly on Mondays at 19:00",
    "raw_time": "19:00",
    "raw_day": "Monday"
  },
  {
    "host_name": "Thamesmead Life Drawing",
    "title": "Thamesmead Life Drawing (Monday)",
    "event_type": "in_person",
    "price_info": "\u00a310",
    "default_duration_mins": 120,
    "recurrence": "Fortnightly on Mondays at 19:00",
    "raw_time": "19:00",
    "raw_day": "Monday"
  },
  {
    "host_name": "Neon Naked Life Drawing",
    "title": "Neon Naked Life Drawing (Saturday)",
    "event_type": "hybrid",
    "price_info": "\u00a317 In-person / \u00a317 Online",
    "default_duration_mins": 90,
    "recurrence": "Weekly on Saturdays at 15:30",
    "raw_time": "15:30",
    "raw_day": "Saturday"
  }
]